LICENSE
MANIFEST.in
README.md
setup.py
django_imagekitio_storage.egg-info/PKG-INFO
django_imagekitio_storage.egg-info/SOURCES.txt
django_imagekitio_storage.egg-info/dependency_links.txt
django_imagekitio_storage.egg-info/requires.txt
django_imagekitio_storage.egg-info/top_level.txt
imagekitio_storage/__init__.py
imagekitio_storage/app_settings.py
imagekitio_storage/apps.py
imagekitio_storage/defaults.py
imagekitio_storage/delete.py
imagekitio_storage/errors.py
imagekitio_storage/helpers.py
imagekitio_storage/resource.py
imagekitio_storage/storage.py
imagekitio_storage/validators.py
imagekitio_storage/management/__init__.py
imagekitio_storage/management/commands/__init__.py
imagekitio_storage/management/commands/collectstatic.py
imagekitio_storage/templatetags/__init__.py
imagekitio_storage/templatetags/imagekit_static.py