Metadata-Version: 2.1
Name: django-imagekitio-storage
Version: 0.0.1
Summary: Django package that provides Imagekit storages for both media and static files and management commands for removing unnecessary files.
Home-page: https://github.com/envframe/django-imagekit-storage
Author: Envframe
Author-email: envframe@gmail.com
License: MIT
Keywords: django imagekit storage
Platform: UNKNOWN
Classifier: Environment :: Web Environment
Classifier: Framework :: Django
Classifier: Intended Audience :: Developers
Classifier: Operating System :: OS Independent
Classifier: Programming Language :: Python
Classifier: Programming Language :: Python :: 3
Classifier: Programming Language :: Python :: 3.5
Classifier: Programming Language :: Python :: 3.6
Classifier: Programming Language :: Python :: 3.7
Classifier: Programming Language :: Python :: 3.8
Classifier: Topic :: Internet :: WWW/HTTP
Provides-Extra: video
License-File: LICENSE
